hammerspoon_bridge/__init__.py
hammerspoon_bridge-1.0.0.dist-info/LICENSE
hammerspoon_bridge-1.0.0.dist-info/METADATA
hammerspoon_bridge-1.0.0.dist-info/WHEEL
hammerspoon_bridge-1.0.0.dist-info/top_level.txt
hammerspoon_bridge-1.0.0.dist-info/RECORD
