Metadata-Version: 2.1
Name: hammerspoon_bridge
Version: 1.0.0
Summary: Interoperate with Hammerspoon through its CLI
Home-page: https://github.com/AaronC81/hammerspoon_bridge
Author: Aaron Christiansen
Author-email: aaronc20000@gmail.com
Classifier: Programming Language :: Python :: 3
Classifier: License :: OSI Approved :: MIT License
Classifier: Operating System :: MacOS
Classifier: Topic :: Utilities
Classifier: Programming Language :: Other Scripting Engines
Requires-Python: >=3.7
License-File: LICENSE
